wavespeed/__init__.py
wavespeed/_config_module.py
wavespeed/_version.py
wavespeed/config.py
wavespeed/api/__init__.py
wavespeed/api/client.py
wavespeed/serverless/__init__.py
wavespeed/serverless/worker.py
wavespeed/serverless/modules/__init__.py
wavespeed/serverless/modules/fastapi.py
wavespeed/serverless/modules/handler.py
wavespeed/serverless/modules/heartbeat.py
wavespeed/serverless/modules/http.py
wavespeed/serverless/modules/job.py
wavespeed/serverless/modules/local.py
wavespeed/serverless/modules/logger.py
wavespeed/serverless/modules/progress.py
wavespeed/serverless/modules/scaler.py
wavespeed/serverless/modules/state.py
wavespeed/serverless/utils/__init__.py
wavespeed/serverless/utils/boto3_utils.py
wavespeed/serverless/utils/validator.py
wavespeed-1.0.7.dist-info/licenses/LICENSE
wavespeed-1.0.7.dist-info/METADATA
wavespeed-1.0.7.dist-info/WHEEL
wavespeed-1.0.7.dist-info/top_level.txt
wavespeed-1.0.7.dist-info/RECORD
