Metadata-Version: 2.4
Name: wavespeed
Version: 1.0.7
Summary: WaveSpeedAI Python Client — Official Python SDK for WaveSpeedAI inference platform
Author-email: WaveSpeedAI <support@wavespeed.ai>
License: MIT
Project-URL: Homepage, https://github.com/WaveSpeedAI/wavespeed-python
Project-URL: Repository, https://github.com/WaveSpeedAI/wavespeed-python
Project-URL: Issues, https://github.com/WaveSpeedAI/wavespeed-python/issues
Classifier: Development Status :: 3 - Alpha
Classifier: Intended Audience :: Developers
Classifier: License :: OSI Approved :: MIT License
Classifier: Programming Language :: Python :: 3
Classifier: Programming Language :: Python :: 3.8
Classifier: Programming Language :: Python :: 3.9
Classifier: Programming Language :: Python :: 3.10
Classifier: Programming Language :: Python :: 3.11
Classifier: Programming Language :: Python :: 3.12
Requires-Python: >=3.8
License-File: LICENSE
Requires-Dist: aiohttp[speedups]>=3.9.3
Requires-Dist: aiohttp-retry>=2.8.3
Requires-Dist: requests>=2.25.0
Requires-Dist: boto3>=1.26.165
Provides-Extra: test
Requires-Dist: pytest; extra == "test"
Dynamic: license-file
